build/lib/doc/source/conf.py
build/lib/rstbuddy/__init__.py
build/lib/rstbuddy/exc.py
build/lib/rstbuddy/main.py
build/lib/rstbuddy/py.typed
build/lib/rstbuddy/settings.py
build/lib/rstbuddy/types.py
build/lib/rstbuddy/cli/__init__.py
build/lib/rstbuddy/cli/check_links.py
build/lib/rstbuddy/cli/cli.py
build/lib/rstbuddy/cli/fix.py
build/lib/rstbuddy/cli/gather_links.py
build/lib/rstbuddy/cli/summarize.py
build/lib/rstbuddy/cli/utils.py
build/lib/rstbuddy/models/__init__.py
build/lib/rstbuddy/models/check_links.py
build/lib/rstbuddy/models/clean.py
build/lib/rstbuddy/services/__init__.py
build/lib/rstbuddy/services/gather_links.py
build/lib/rstbuddy/services/pandoc_converter.py
build/lib/rstbuddy/services/rst_cleaner.py
build/lib/rstbuddy/services/rst_link_checker.py
build/lib/rstbuddy/services/summary_generation.py
build/lib/tests/__init__.py
build/lib/tests/conftest.py
build/lib/tests/test_cli_check_links.py
build/lib/tests/test_cli_commands.py
build/lib/tests/test_cli_fix.py
build/lib/tests/test_cli_gather_links.py
build/lib/tests/test_cli_summarize.py
build/lib/tests/test_cli_utils.py
build/lib/tests/test_configuration.py
build/lib/tests/test_main.py
build/lib/tests/test_models_clean.py
build/lib/tests/test_pandoc_converter.py
build/lib/tests/test_pandoc_converter_coverage.py
build/lib/tests/test_performance_summary_generation.py
build/lib/tests/test_ref_functionality.py
build/lib/tests/test_rst_cleaner.py
build/lib/tests/test_rst_cleaner_extended.py
build/lib/tests/test_rst_link_checker_extended.py
build/lib/tests/test_summary_generation.py
build/lib/tests/test_summary_generation_extended.py
doc/source/conf.py
rstbuddy/__init__.py
rstbuddy/exc.py
rstbuddy/main.py
rstbuddy/py.typed
rstbuddy/settings.py
rstbuddy/types.py
rstbuddy/cli/__init__.py
rstbuddy/cli/check_links.py
rstbuddy/cli/cli.py
rstbuddy/cli/fix.py
rstbuddy/cli/gather_links.py
rstbuddy/cli/summarize.py
rstbuddy/cli/utils.py
rstbuddy/models/__init__.py
rstbuddy/models/check_links.py
rstbuddy-0.3.1.dist-info/licenses/AUTHORS.txt
rstbuddy-0.3.1.dist-info/licenses/LICENSE.txt
rstbuddy-0.3.1.dist-info/METADATA
rstbuddy-0.3.1.dist-info/WHEEL
rstbuddy-0.3.1.dist-info/entry_points.txt
rstbuddy-0.3.1.dist-info/top_level.txt
rstbuddy-0.3.1.dist-info/RECORD
