Metadata-Version: 2.4
Name: rstbuddy
Version: 0.3.1
Summary: A tool for ensuring your strucuredText files are (more) syntactically correct
Author-email: Chris Malek <cmalek@caltech.edu>
Maintainer-email: Chris Malek <cmalek@caltech.edu>
Project-URL: Respository, https://github.com/caltechads/rstbuddy
Project-URL: Documentation, https://rstbuddy.readthedocs.io
Project-URL: Issues, https://github.com/caltechads/rstbuddy/issues
Classifier: Development Status :: 3 - Alpha
Classifier: Intended Audience :: Developers
Classifier: Operating System :: OS Independent
Classifier: Programming Language :: Python
Classifier: Programming Language :: Python :: 3.11
Classifier: Programming Language :: Python :: 3.12
Classifier: Programming Language :: Python :: 3.13
Classifier: Topic :: Utilities
Classifier: Typing :: Typed
Requires-Python: >=3.11
License-File: LICENSE.txt
License-File: AUTHORS.txt
Requires-Dist: click>=8.1.7
Requires-Dist: rich>=13.8.1
Requires-Dist: pydantic>=2.10.6
Requires-Dist: pydantic-settings>=2.5.2
Requires-Dist: build>=1.2.2.post1
Requires-Dist: openai>=1.99.6
Requires-Dist: mdformat>=0.7.22
Dynamic: license-file
